{
  "nodes": {
    "gitlab.example.com": {
      ":ip": "192.168.32.5",
      "ports": [],
      ":memory": 1024,
      ":bootstrap": "bootstrap.sh"
    },
    "gitserver.example.com": {
      ":ip": "192.168.32.10",
      "ports": [],
      ":memory": 3072,
      ":bootstrap": "bootstrap.sh"
    },
    "JenkinsAgent.com": {
      ":ip": "192.168.32.20",
      "ports": [],
      ":memory": 1024,
      ":bootstrap": "bootstrap.sh"
    },
    "NexusRepo.com": {
      ":ip": "192.168.32.30",
      "ports": [],
      ":memory": 1024,
      ":bootstrap": "bootstrap.sh"
    }
  }
}
